pigstep/__init__.py
pigstep/note.py
pigstep/plugin.py
pigstep/py.typed
pigstep/sounds/__init__.py
pigstep/sounds/banjo_-1.ogg
pigstep/sounds/banjo_1.ogg
pigstep/sounds/basedrum_-1.ogg
pigstep/sounds/basedrum_1.ogg
pigstep/sounds/bassattack_-1.ogg
pigstep/sounds/bassattack_1.ogg
pigstep/sounds/bell_-1.ogg
pigstep/sounds/bell_1.ogg
pigstep/sounds/bit_-1.ogg
pigstep/sounds/bit_1.ogg
pigstep/sounds/cow_bell_-1.ogg
pigstep/sounds/cow_bell_1.ogg
pigstep/sounds/didgeridoo_-1.ogg
pigstep/sounds/didgeridoo_1.ogg
pigstep/sounds/flute_-1.ogg
pigstep/sounds/flute_1.ogg
pigstep/sounds/guitar_-1.ogg
pigstep/sounds/guitar_1.ogg
pigstep/sounds/harp_-1.ogg
pigstep/sounds/harp_1.ogg
pigstep/sounds/hat_-1.ogg
pigstep/sounds/hat_1.ogg
pigstep/sounds/icechime_-1.ogg
pigstep/sounds/icechime_1.ogg
pigstep/sounds/iron_xylophone_-1.ogg
pigstep/sounds/iron_xylophone_1.ogg
pigstep/sounds/pling_-1.ogg
pigstep/sounds/pling_1.ogg
pigstep/sounds/snare_-1.ogg
pigstep/sounds/snare_1.ogg
pigstep/sounds/xylobone_-1.ogg
pigstep/sounds/xylobone_1.ogg
pigstep/templates/pause.mcfunction
pigstep/templates/play.mcfunction
pigstep/templates/stop.mcfunction
pigstep/templates/tick.mcfunction
pigstep-0.2.1.dist-info/entry_points.txt
pigstep-0.2.1.dist-info/LICENSE
pigstep-0.2.1.dist-info/WHEEL
pigstep-0.2.1.dist-info/METADATA
pigstep-0.2.1.dist-info/RECORD
