Metadata-Version: 2.1
Name: pigstep
Version: 0.2.1
Summary: A beet plugin for importing songs into Minecraft
Home-page: https://github.com/vberlier/pigstep
License: MIT
Keywords: beet,minecraft,note-block-studio
Author: Valentin Berlier
Author-email: berlier.v@gmail.com
Requires-Python: >=3.8,<4.0
Classifier: License :: OSI Approved :: MIT License
Classifier: Programming Language :: Python :: 3
Classifier: Programming Language :: Python :: 3.8
Classifier: Programming Language :: Python :: 3.9
Requires-Dist: beet (>=0.22.0)
Requires-Dist: pynbs (>=0.4.2,<0.5.0)
Project-URL: Documentation, https://github.com/vberlier/pigstep
Project-URL: Repository, https://github.com/vberlier/pigstep
